setup.py
.venv/bin/activate_this.py
.venv/bin/jp.py
.venv/bin/rst2html.py
.venv/bin/rst2html4.py
.venv/bin/rst2html5.py
.venv/bin/rst2latex.py
.venv/bin/rst2man.py
.venv/bin/rst2odt.py
.venv/bin/rst2odt_prepstyles.py
.venv/bin/rst2pseudoxml.py
.venv/bin/rst2s5.py
.venv/bin/rst2xetex.py
.venv/bin/rst2xml.py
.venv/bin/rstpep2html.py
.venv/lib/python3.12/site-packages/_virtualenv.py
.venv/lib/python3.12/site-packages/six.py
.venv/lib/python3.12/site-packages/PyYAML-6.0.1.dist-info/top_level.txt
.venv/lib/python3.12/site-packages/_distutils_hack/__init__.py
.venv/lib/python3.12/site-packages/_distutils_hack/override.py
.venv/lib/python3.12/site-packages/_yaml/__init__.py
.venv/lib/python3.12/site-packages/awscli/__init__.py
.venv/lib/python3.12/site-packages/awscli/__main__.py
.venv/lib/python3.12/site-packages/awscli/alias.py
.venv/lib/python3.12/site-packages/awscli/argparser.py
.venv/lib/python3.12/site-packages/awscli/argprocess.py
.venv/lib/python3.12/site-packages/awscli/arguments.py
.venv/lib/python3.12/site-packages/awscli/clidocs.py
.venv/lib/python3.12/site-packages/awscli/clidriver.py
.venv/lib/python3.12/site-packages/awscli/commands.py
.venv/lib/python3.12/site-packages/awscli/compat.py
.venv/lib/python3.12/site-packages/awscli/completer.py
.venv/lib/python3.12/site-packages/awscli/errorhandler.py
.venv/lib/python3.12/site-packages/awscli/formatter.py
.venv/lib/python3.12/site-packages/awscli/handlers.py
.venv/lib/python3.12/site-packages/awscli/help.py
.venv/lib/python3.12/site-packages/awscli/paramfile.py
.venv/lib/python3.12/site-packages/awscli/plugin.py
.venv/lib/python3.12/site-packages/awscli/schema.py
.venv/lib/python3.12/site-packages/awscli/shorthand.py
.venv/lib/python3.12/site-packages/awscli/table.py
.venv/lib/python3.12/site-packages/awscli/testutils.py
.venv/lib/python3.12/site-packages/awscli/text.py
.venv/lib/python3.12/site-packages/awscli/topictags.py
.venv/lib/python3.12/site-packages/awscli/utils.py
.venv/lib/python3.12/site-packages/awscli-1.32.91.dist-info/LICENSE.txt
.venv/lib/python3.12/site-packages/awscli-1.32.91.dist-info/top_level.txt
.venv/lib/python3.12/site-packages/awscli/bcdoc/__init__.py
.venv/lib/python3.12/site-packages/botocore-1.34.91.dist-info/LICENSE.txt
.venv/lib/python3.12/site-packages/botocore-1.34.91.dist-info/top_level.txt
.venv/lib/python3.12/site-packages/certifi-2024.2.2.dist-info/top_level.txt
.venv/lib/python3.12/site-packages/charset_normalizer-3.3.2.dist-info/entry_points.txt
.venv/lib/python3.12/site-packages/charset_normalizer-3.3.2.dist-info/top_level.txt
.venv/lib/python3.12/site-packages/colorama-0.4.4.dist-info/LICENSE.txt
.venv/lib/python3.12/site-packages/colorama-0.4.4.dist-info/top_level.txt
.venv/lib/python3.12/site-packages/docutils-0.16.dist-info/COPYING.txt
.venv/lib/python3.12/site-packages/docutils-0.16.dist-info/top_level.txt
.venv/lib/python3.12/site-packages/importlib_metadata-7.1.0.dist-info/top_level.txt
.venv/lib/python3.12/site-packages/jaraco.classes-3.4.0.dist-info/top_level.txt
.venv/lib/python3.12/site-packages/jaraco.context-5.3.0.dist-info/top_level.txt
.venv/lib/python3.12/site-packages/jaraco.functools-4.0.1.dist-info/top_level.txt
.venv/lib/python3.12/site-packages/jmespath-1.0.1.dist-info/LICENSE.txt
.venv/lib/python3.12/site-packages/jmespath-1.0.1.dist-info/top_level.txt
.venv/lib/python3.12/site-packages/keyring-25.1.0.dist-info/entry_points.txt
.venv/lib/python3.12/site-packages/keyring-25.1.0.dist-info/top_level.txt
.venv/lib/python3.12/site-packages/markdown_it_py-3.0.0.dist-info/entry_points.txt
.venv/lib/python3.12/site-packages/pip-23.2.1.dist-info/AUTHORS.txt
.venv/lib/python3.12/site-packages/pip-23.2.1.dist-info/LICENSE.txt
.venv/lib/python3.12/site-packages/pip-23.2.1.dist-info/entry_points.txt
.venv/lib/python3.12/site-packages/pip-23.2.1.dist-info/top_level.txt
.venv/lib/python3.12/site-packages/pkginfo-1.10.0.dist-info/LICENSE.txt
.venv/lib/python3.12/site-packages/pkginfo-1.10.0.dist-info/entry_points.txt
.venv/lib/python3.12/site-packages/pkginfo-1.10.0.dist-info/top_level.txt
.venv/lib/python3.12/site-packages/pyasn1-0.6.0.dist-info/top_level.txt
.venv/lib/python3.12/site-packages/pygments-2.17.2.dist-info/entry_points.txt
.venv/lib/python3.12/site-packages/python_dateutil-2.9.0.post0.dist-info/top_level.txt
.venv/lib/python3.12/site-packages/python_dotenv-1.0.1.dist-info/entry_points.txt
.venv/lib/python3.12/site-packages/python_dotenv-1.0.1.dist-info/top_level.txt
.venv/lib/python3.12/site-packages/readme_renderer-43.0.dist-info/top_level.txt
.venv/lib/python3.12/site-packages/requests-2.31.0.dist-info/top_level.txt
.venv/lib/python3.12/site-packages/requests_toolbelt-1.0.0.dist-info/top_level.txt
.venv/lib/python3.12/site-packages/rfc3986-2.0.0.dist-info/top_level.txt
.venv/lib/python3.12/site-packages/rsa-4.7.2.dist-info/entry_points.txt
.venv/lib/python3.12/site-packages/rsa-4.7.2.dist-info/top_level.txt
.venv/lib/python3.12/site-packages/s3transfer-0.10.1.dist-info/LICENSE.txt
.venv/lib/python3.12/site-packages/s3transfer-0.10.1.dist-info/NOTICE.txt
.venv/lib/python3.12/site-packages/s3transfer-0.10.1.dist-info/top_level.txt
.venv/lib/python3.12/site-packages/satsure_cloud_utils-0.0.26.dist-info/top_level.txt
.venv/lib/python3.12/site-packages/setuptools-69.5.1.dist-info/entry_points.txt
.venv/lib/python3.12/site-packages/setuptools-69.5.1.dist-info/top_level.txt
.venv/lib/python3.12/site-packages/six-1.16.0.dist-info/top_level.txt
.venv/lib/python3.12/site-packages/twine-5.0.0.dist-info/entry_points.txt
.venv/lib/python3.12/site-packages/twine-5.0.0.dist-info/top_level.txt
.venv/lib/python3.12/site-packages/urllib3-2.2.1.dist-info/licenses/LICENSE.txt
.venv/lib/python3.12/site-packages/zipp-3.18.1.dist-info/top_level.txt
simplecalculatorkms.egg-info/PKG-INFO
simplecalculatorkms.egg-info/SOURCES.txt
simplecalculatorkms.egg-info/dependency_links.txt
simplecalculatorkms.egg-info/top_level.txt