Metadata-Version: 2.1
Name: simplecalculatorkms
Version: 0.0.4
Summary: A very basic simplecalculatorkms
Home-page: 
Author: meenakshisundaram
Author-email: kmstpm@gamil.org
Keywords: simplecalculatorkms
Classifier: Development Status :: 5 - Production/Stable
Classifier: Intended Audience :: Education
Classifier: Programming Language :: Python :: 3
